starship_loader/__init__.py
starship_loader/swapi.py
sw_journey_planner/__init__.py
sw_journey_planner/command_line.py
sw_journey_planner/starship.py
sw_journey_planner/swapi.py
test/__init__.py
test/test_starship.py
test/test_swapi_convert_consumables_to_hours.py
test/test_swapi_create_starship.py
test/test_swapi_load_starships.py
test/test_swapi_parse_consumables.py
sw_journey_planner-1.0.5.dist-info/METADATA
sw_journey_planner-1.0.5.dist-info/WHEEL
sw_journey_planner-1.0.5.dist-info/entry_points.txt
sw_journey_planner-1.0.5.dist-info/top_level.txt
sw_journey_planner-1.0.5.dist-info/RECORD
