Metadata-Version: 2.1
Name: sw-journey-planner
Version: 1.0.5
Summary: A StarWars journey planner
Home-page: UNKNOWN
Author: UNKNOWN
Author-email: UNKNOWN
License: UNKNOWN
Platform: UNKNOWN
